product_plan_canvas/__init__.py
product_plan_canvas/component.py
product_plan_canvas-0.1.0.dist-info/METADATA
product_plan_canvas-0.1.0.dist-info/WHEEL
product_plan_canvas-0.1.0.dist-info/RECORD
