Metadata-Version: 2.4
Name: product_plan_canvas
Version: 0.1.0
Summary: A custom Gradio component for product planning with a 4-column drag-and-drop board
Project-URL: Homepage, https://github.com/yourusername/product-plan-canvas
Project-URL: Bug Tracker, https://github.com/yourusername/product-plan-canvas/issues
Author: AutoPilot PM Team
License-Expression: MIT
Classifier: Development Status :: 4 - Beta
Classifier: Intended Audience :: Developers
Classifier: License :: OSI Approved :: MIT License
Classifier: Programming Language :: Python :: 3
Classifier: Programming Language :: Python :: 3.8
Classifier: Programming Language :: Python :: 3.9
Classifier: Programming Language :: Python :: 3.10
Classifier: Programming Language :: Python :: 3.11
Requires-Python: >=3.8
Requires-Dist: gradio>=4.0.0
Requires-Dist: typing-extensions>=4.0.0
